[
    {
        "id":"01",
        "productName":"one",
        "price":"50",
        "reviews":[
            {
                "reviewId" : "1",
                "review" : "Very good product 1"
            },
            {
                "reviewId" : "2",
                "review" : "Very good product 2"
            },
            {
                "reviewId" : "3",
                "review" : "Very good product 3"
            },
            {
                "reviewId" : "4",
                "review" : "Very good product 4"
            }
            
        ]
    },
    {
        "id":"02",
        "productName":"two",
        "price":"100",
        "reviews":[
            {
                "reviewId" : "1",
                "review" : "Very good product 1"
            },
            {
                "reviewId" : "2",
                "review" : "Very good product 2"
            },
            {
                "reviewId" : "3",
                "review" : "Very good product 3"
            },
            {
                "reviewId" : "4",
                "review" : "Very good product 4"
            }
            
        ]
    },
    {
        "id":"03",
        "productName":"three",
        "price":"150",
        "reviews":[
            {
                "reviewId" : "1",
                "review" : "Very good product 1"
            },
            {
                "reviewId" : "2",
                "review" : "Very good product 2"
            },
            {
                "reviewId" : "3",
                "review" : "Very good product 3"
            },
            {
                "reviewId" : "4",
                "review" : "Very good product 4"
            }
            
        ]
    },
    {
        "id":"04",
        "productName":"four",
        "price":"200",
        "reviews":[
            {
                "reviewId" : "1",
                "review" : "Very good product 1"
            },
            {
                "reviewId" : "2",
                "review" : "Very good product 2"
            },
            {
                "reviewId" : "3",
                "review" : "Very good product 3"
            },
            {
                "reviewId" : "4",
                "review" : "Very good product 4"
            }
            
        ]
    },
    {
        "id":"05",
        "productName":"five",
        "price":"250",
        "reviews":[
            {
                "reviewId" : "1",
                "review" : "Very good product 1"
            },
            {
                "reviewId" : "2",
                "review" : "Very good product 2"
            },
            {
                "reviewId" : "3",
                "review" : "Very good product 3"
            },
            {
                "reviewId" : "4",
                "review" : "Very good product 4"
            }
            
        ]
    },
    {
        "id":"06",
        "productName":"six",
        "price":"300",
        "reviews":[
            {
                "reviewId" : "1",
                "review" : "Very good product 1"
            },
            {
                "reviewId" : "2",
                "review" : "Very good product 2"
            },
            {
                "reviewId" : "3",
                "review" : "Very good product 3"
            },
            {
                "reviewId" : "4",
                "review" : "Very good product 4"
            }
            
        ]
    },
    {
        "id":"07",
        "productName":"seven",
        "price":"350",
        "reviews":[
            {
                "reviewId" : "1",
                "review" : "Very good product 1"
            },
            {
                "reviewId" : "2",
                "review" : "Very good product 2"
            },
            {
                "reviewId" : "3",
                "review" : "Very good product 3"
            },
            {
                "reviewId" : "4",
                "review" : "Very good product 4"
            }
            
        ]
    },
    {
        "id":"08",
        "productName":"eight",
        "price":"400",
        "reviews":[
            {
                "reviewId" : "1",
                "review" : "Very good product 1"
            },
            {
                "reviewId" : "2",
                "review" : "Very good product 2"
            },
            {
                "reviewId" : "3",
                "review" : "Very good product 3"
            },
            {
                "reviewId" : "4",
                "review" : "Very good product 4"
            }
            
        ]
    },
    {
        "id":"09",
        "productName":"nine",
        "price":"450",
        "reviews":[
            {
                "reviewId" : "1",
                "review" : "Very good product 1"
            },
            {
                "reviewId" : "2",
                "review" : "Very good product 2"
            },
            {
                "reviewId" : "3",
                "review" : "Very good product 3"
            },
            {
                "reviewId" : "4",
                "review" : "Very good product 4"
            },
            {
                "reviewId" : "5",
                "review" : "Very good product 5"
            },
            {
                "reviewId" : "6",
                "review" : "Very good product 6"
            }
        ]
    },
    {
        "id":"10",
        "productName":"nine",
        "price":"450",
        "reviews":[
            {
                "reviewId" : "1",
                "review" : "Very good product 1"
            },
            {
                "reviewId" : "2",
                "review" : "Very good product 2"
            },
            {
                "reviewId" : "3",
                "review" : "Very good product 3"
            },
            {
                "reviewId" : "4",
                "review" : "Very good product 4"
            },
            {
                "reviewId" : "5",
                "review" : "Very good product 5"
            },
            {
                "reviewId" : "6",
                "review" : "Very good product 6"
            }
        ]
    },
    {
        "id":"11",
        "productName":"nine",
        "price":"450",
        "reviews":[
            {
                "reviewId" : "1",
                "review" : "Very good product 1"
            },
            {
                "reviewId" : "2",
                "review" : "Very good product 2"
            },
            {
                "reviewId" : "3",
                "review" : "Very good product 3"
            },
            {
                "reviewId" : "4",
                "review" : "Very good product 4"
            },
            {
                "reviewId" : "5",
                "review" : "Very good product 5"
            },
            {
                "reviewId" : "6",
                "review" : "Very good product 6"
            }
        ]
    },
    {
        "id":"12",
        "productName":"nine",
        "price":"450",
        "reviews":[
            {
                "reviewId" : "1",
                "review" : "Very good product 1"
            },
            {
                "reviewId" : "2",
                "review" : "Very good product 2"
            },
            {
                "reviewId" : "3",
                "review" : "Very good product 3"
            },
            {
                "reviewId" : "4",
                "review" : "Very good product 4"
            },
            {
                "reviewId" : "5",
                "review" : "Very good product 5"
            },
            {
                "reviewId" : "6",
                "review" : "Very good product 6"
            }
        ]
    },
    {
        "id":"13",
        "productName":"nine",
        "price":"450",
        "reviews":[
            {
                "reviewId" : "1",
                "review" : "Very good product 1"
            },
            {
                "reviewId" : "2",
                "review" : "Very good product 2"
            },
            {
                "reviewId" : "3",
                "review" : "Very good product 3"
            },
            {
                "reviewId" : "4",
                "review" : "Very good product 4"
            },
            {
                "reviewId" : "5",
                "review" : "Very good product 5"
            },
            {
                "reviewId" : "6",
                "review" : "Very good product 6"
            }
        ]
    },
    {
        "id":"14",
        "productName":"nine",
        "price":"450",
        "reviews":[
            {
                "reviewId" : "1",
                "review" : "Very good product 1"
            },
            {
                "reviewId" : "2",
                "review" : "Very good product 2"
            },
            {
                "reviewId" : "3",
                "review" : "Very good product 3"
            },
            {
                "reviewId" : "4",
                "review" : "Very good product 4"
            },
            {
                "reviewId" : "5",
                "review" : "Very good product 5"
            },
            {
                "reviewId" : "6",
                "review" : "Very good product 6"
            }
        ]
    },
    {
        "id":"15",
        "productName":"nine",
        "price":"450",
        "reviews":[
            {
                "reviewId" : "1",
                "review" : "Very good product 1"
            },
            {
                "reviewId" : "2",
                "review" : "Very good product 2"
            },
            {
                "reviewId" : "3",
                "review" : "Very good product 3"
            },
            {
                "reviewId" : "4",
                "review" : "Very good product 4"
            },
            {
                "reviewId" : "5",
                "review" : "Very good product 5"
            },
            {
                "reviewId" : "6",
                "review" : "Very good product 6"
            }
        ]
    },
    {
        "id":"16",
        "productName":"nine",
        "price":"450",
        "reviews":[
            {
                "reviewId" : "1",
                "review" : "Very good product 1"
            },
            {
                "reviewId" : "2",
                "review" : "Very good product 2"
            },
            {
                "reviewId" : "3",
                "review" : "Very good product 3"
            },
            {
                "reviewId" : "4",
                "review" : "Very good product 4"
            },
            {
                "reviewId" : "5",
                "review" : "Very good product 5"
            },
            {
                "reviewId" : "6",
                "review" : "Very good product 6"
            }
        ]
    },
    {
        "id":"17",
        "productName":"nine",
        "price":"450",
        "reviews":[
            {
                "reviewId" : "1",
                "review" : "Very good product 1"
            },
            {
                "reviewId" : "2",
                "review" : "Very good product 2"
            },
            {
                "reviewId" : "3",
                "review" : "Very good product 3"
            },
            {
                "reviewId" : "4",
                "review" : "Very good product 4"
            },
            {
                "reviewId" : "5",
                "review" : "Very good product 5"
            },
            {
                "reviewId" : "6",
                "review" : "Very good product 6"
            }
        ]
    },
    {
        "id":"18",
        "productName":"nine",
        "price":"450",
        "reviews":[
            {
                "reviewId" : "1",
                "review" : "Very good product 1"
            },
            {
                "reviewId" : "2",
                "review" : "Very good product 2"
            },
            {
                "reviewId" : "3",
                "review" : "Very good product 3"
            },
            {
                "reviewId" : "4",
                "review" : "Very good product 4"
            },
            {
                "reviewId" : "5",
                "review" : "Very good product 5"
            },
            {
                "reviewId" : "6",
                "review" : "Very good product 6"
            }
        ]
    },
    {
        "id":"19",
        "productName":"nine",
        "price":"450",
        "reviews":[
            {
                "reviewId" : "1",
                "review" : "Very good product 1"
            },
            {
                "reviewId" : "2",
                "review" : "Very good product 2"
            },
            {
                "reviewId" : "3",
                "review" : "Very good product 3"
            },
            {
                "reviewId" : "4",
                "review" : "Very good product 4"
            },
            {
                "reviewId" : "5",
                "review" : "Very good product 5"
            },
            {
                "reviewId" : "6",
                "review" : "Very good product 6"
            }
        ]
    },
    {
        "id":"20",
        "productName":"nine",
        "price":"450",
        "reviews":[
            {
                "reviewId" : "1",
                "review" : "Very good product 1"
            },
            {
                "reviewId" : "2",
                "review" : "Very good product 2"
            },
            {
                "reviewId" : "3",
                "review" : "Very good product 3"
            },
            {
                "reviewId" : "4",
                "review" : "Very good product 4"
            },
            {
                "reviewId" : "5",
                "review" : "Very good product 5"
            },
            {
                "reviewId" : "6",
                "review" : "Very good product 6"
            }
        ]
    }
]